{
    "article": [
        {
            "type": "text",
            "text": "What features would you expect from a fitness tracker over S$100? A colored OLED display, continuous heart rate tracking and the ability to track swimming maybe? The brand new Honor Band 4 offers all of that, and more, at just S$59. In this article, let’s take a quick look at what it offers."
        },
        {
            "type": "header",
            "text": "Unboxing – Nothing Fanciful"
        },
        {
            "type": "text",
            "text": "Honor Band 4 comes in a cyan box similar to the one for the Honor Band A2. Inside the box, you will find the Honor Band 4, a proprietary charging connector and a very short micro USB cable. There are also 2 booklets, one for warranty and the other is a quick start guide. Nothing special here."
        },
        {
            "type": "imageDouble",
            "text": "https://firebasestorage.googleapis.com/v0/b/logicui-9667a.appspot.com/o/reviews%2Fhonor-band-4-review%2Fimg1.jpg?alt=media&token=e4519333-b71e-4add-9424-5a5d969c0e80"
        },
        {
            "type": "imageDouble",
            "text": "https://firebasestorage.googleapis.com/v0/b/logicui-9667a.appspot.com/o/reviews%2Fhonor-band-4-review%2Fimg2.jpg?alt=media&token=e61f4193-761e-4705-9a50-f07abfcfa41b"
        },
        {
            "type": "header",
            "text": "Setup & App – Surprisingly Straightforward"
        },
        {
            "type": "text",
            "text": "Firstly, power on the band by connecting it to the charger. Then, you will be asked to download the Huawei Health app. You can find the app by scanning the QR code on the display, or via one of the links below. Android users will also have to install Huawei Mobile Services from the Play Store."
        },
        {
            "type": "link",
            "text": "Apple App Store",
            "link": "https://apps.apple.com/us/app/huawei-health/id1325481372"
        },
        {
            "type": "link",
            "text": "Google Play Store",
            "link": "https://play.google.com/store/apps/details?id=com.huawei.health&hl=en_SG"
        },
        {
            "type": "link",
            "text": "Huawei App Gallery",
            "link": "https://play.google.com/store/apps/details?id=com.huawei.hwid&hl=en_SG"
        },
        {
            "type": "text",
            "text": "Open the app and register/login to your Huawei account. Once done, tap on the plus icon on top and select “Smart Band”, then “Honor Band 4”. You should see the following icons on the Honor Band 4’s screen. Tap on the tick to pair the band to your phone. Almost done."
        },
        {
            "type": "imageSingle",
            "text": "https://firebasestorage.googleapis.com/v0/b/logicui-9667a.appspot.com/o/reviews%2Fhonor-band-4-review%2Fimg3.jpg?alt=media&token=ce89b4be-78a9-4611-944c-55033ec21bbc"
        },
        {
            "type": "text",
            "text": "Next, it will ask you to set up notifications and other stuff, and lastly update your band’s firmware. The first time I updated it, it took really long but the device stayed cool and used only 10% battery."
        },
        {
            "type": "imageSingle",
            "text": "https://firebasestorage.googleapis.com/v0/b/logicui-9667a.appspot.com/o/reviews%2Fhonor-band-4-review%2Fimg4.jpg?alt=media&token=00a7d4eb-ccef-49a9-8106-a7c56b14c428"
        },
        {
            "type": "text",
            "text": "On top of viewing of data, there are a few settings that you can change in the app. But before you do that, go set your weight and height under “Me” > “Profile”. To change the band’s settings, tap on the band icon on top. Here, you can select what notifications and functions to show on the band."
        },
        {
            "type": "imageQuad",
            "text": "https://firebasestorage.googleapis.com/v0/b/logicui-9667a.appspot.com/o/reviews%2Fhonor-band-4-review%2Fimg5.jpg?alt=media&token=8e8ff86d-a4dc-4a3b-a4c0-915e0f544fe3"
        },
        {
            "type": "imageQuad",
            "text": "https://firebasestorage.googleapis.com/v0/b/logicui-9667a.appspot.com/o/reviews%2Fhonor-band-4-review%2Fimg6.jpg?alt=media&token=f25a910d-c1f2-4b60-9fce-ae765a17340a"
        },
        {
            "type": "imageQuad",
            "text": "https://firebasestorage.googleapis.com/v0/b/logicui-9667a.appspot.com/o/reviews%2Fhonor-band-4-review%2Fimg7.jpg?alt=media&token=66c1fc2f-06aa-4250-a4ca-7c0895782dd2"
        },
        {
            "type": "imageQuad",
            "text": "https://firebasestorage.googleapis.com/v0/b/logicui-9667a.appspot.com/o/reviews%2Fhonor-band-4-review%2Fimg8.jpg?alt=media&token=dc2627b8-bf25-4e05-aed2-43c1a51150c5"
        },
        {
            "type": "text",
            "text": "There are also 2 important features that you can enable: Huawei TruSleep and continuous heart rate tracking. Both features will drain battery faster, but they can help you take fitness tracking to the next level, so you will want to turn them on. I will be talking more about both of them below."
        },
        {
            "type": "text",
            "text": "Overall, the Huawei Health app is well implemented and easy to use. Syncing is really quick too."
        },
        {
            "type": "header",
            "text": "Design – Practical & Comfortable"
        },
        {
            "type": "subheader",
            "text": "Straps"
        },
        {
            "type": "text",
            "text": "Before I get to that beautiful AMOLED display, I want to talk about the straps. It is very flexible and comfortable around your wrist. Holes on both straps allow for greater ventilation. Unlike the Xiaomi’s strap, Honor Band 4’s strap buckle is made of hard plastic, so it wouldn’t break so easily."
        },
        {
            "type": "imageDouble",
            "text": "https://firebasestorage.googleapis.com/v0/b/logicui-9667a.appspot.com/o/reviews%2Fhonor-band-4-review%2Fimg9.jpg?alt=media&token=6de9f02c-3680-4987-976e-86d52af5020d"
        },
        {
            "type": "imageDouble",
            "text": "https://firebasestorage.googleapis.com/v0/b/logicui-9667a.appspot.com/o/reviews%2Fhonor-band-4-review%2Fimg10.jpg?alt=media&token=7371db20-5e26-4297-a819-9cddfff2e51d"
        },
        {
            "type": "text",
            "text": "In Singapore, there are only 2 colors for the strap: blue and black. But if you so happen to find a nicer one, you can remove and replace it by following the steps below. No tools needed."
        },
        {
            "type": "imageSingle",
            "text": "https://firebasestorage.googleapis.com/v0/b/logicui-9667a.appspot.com/o/reviews%2Fhonor-band-4-review%2Fimg11.jpg?alt=media&token=dc67fe6d-6ebb-4100-bbc5-12a64f035134"
        },
        {
            "type": "subheader",
            "text": "Screen"
        },
        {
            "type": "text",
            "text": "To the front is the screen and a capacitive button below it. The colored screen is well-sized for a fitness tracker, plenty sharp and is bright enough to be seen under direct sunlight. Yep, even though it is only S$4 more than the Mi Band 3, its display has colors! Very impressive, Honor."
        },
        {
            "type": "imageSingle",
            "text": "https://firebasestorage.googleapis.com/v0/b/logicui-9667a.appspot.com/o/reviews%2Fhonor-band-4-review%2Fimg12.jpg?alt=media&token=04946575-33a4-4ec0-bae4-ce3b9977eea6"
        },
        {
            "type": "text",
            "text": "On top of the default watch face, there are 3 other faces available right now, up from just a total of 2 faces at the launch event. We can expect more to come via future firmware updates. Certain faces can display additional information, like weather and distance traveled for example."
        },
        {
            "type": "imageTriple",
            "text": "https://firebasestorage.googleapis.com/v0/b/logicui-9667a.appspot.com/o/reviews%2Fhonor-band-4-review%2Fimg13.jpg?alt=media&token=b8523931-24f9-4715-9039-98e0845e68d6"
        },
        {
            "type": "imageTriple",
            "text": "https://firebasestorage.googleapis.com/v0/b/logicui-9667a.appspot.com/o/reviews%2Fhonor-band-4-review%2Fimg14.jpg?alt=media&token=1c7397e5-0e3f-41bf-a111-d9d1207b8654"
        },
        {
            "type": "imageTriple",
            "text": "https://firebasestorage.googleapis.com/v0/b/logicui-9667a.appspot.com/o/reviews%2Fhonor-band-4-review%2Fimg15.jpg?alt=media&token=cfcd643e-4b5a-4c59-8f8e-0d4ae1557006"
        },
        {
            "type": "text",
            "text": "You interact with the display by swiping and tapping on it. Swipe up and down to navigate through different functions and tap to enter. Swipe from the left to go back. Tap the capacitive button below to wake the screen and return to the watch face. Very straightforward."
        },
        {
            "type": "imageDouble",
            "text": "https://firebasestorage.googleapis.com/v0/b/logicui-9667a.appspot.com/o/reviews%2Fhonor-band-4-review%2Fimg16.gif?alt=media&token=e1d18fb2-98ff-4e08-bafd-4705a08ede4f"
        },
        {
            "type": "imageDouble",
            "text": "https://firebasestorage.googleapis.com/v0/b/logicui-9667a.appspot.com/o/reviews%2Fhonor-band-4-review%2Fimg17.gif?alt=media&token=71b973df-704d-4bd8-a413-ff82f2afcc05"
        },
        {
            "type": "text",
            "text": "The display sleeps after ~8s of inactivity, but it will only return to the watch face after ~20s. No need to tap the screen every few seconds to prevent it from going to sleep and ending your interaction. This small attention to detail greatly improved my experience using the Honor Band 4."
        },
        {
            "type": "imageSingle",
            "text": "https://firebasestorage.googleapis.com/v0/b/logicui-9667a.appspot.com/o/reviews%2Fhonor-band-4-review%2Fimg18.gif?alt=media&token=42153665-e7e8-42a3-bc81-9eb18bf862dd"
        },
        {
            "type": "subheader",
            "text": "Main Body"
        },
        {
            "type": "text",
            "text": "The plastic body of Honor Band 4 is matte on the back, clear and glossy on the front. It feels well built. On the rear, we have a heart rate monitor, as well as two metal connectors for charging."
        },
        {
            "type": "imageSingle",
            "text": "https://firebasestorage.googleapis.com/v0/b/logicui-9667a.appspot.com/o/reviews%2Fhonor-band-4-review%2Fimg19.jpg?alt=media&token=39d22e6e-7a2a-45d7-b8f4-eaa20431a60f"
        },
        {
            "type": "text",
            "text": "Honor Band 4’s water resistance is rated up to 50m, so you can bring it for a swim. The display wouldn’t register your taps and swipes under water, but you can enable “Rotate to switch screen” to switch page."
        },
        {
            "type": "imageSingle",
            "text": "https://firebasestorage.googleapis.com/v0/b/logicui-9667a.appspot.com/o/reviews%2Fhonor-band-4-review%2Fimg20.gif?alt=media&token=ab14bac7-c30f-44dd-a84a-9b41feb1318e"
        },
        {
            "type": "header",
            "text": "Step Tracking – Not Too Shabby"
        },
        {
            "type": "text",
            "text": "So far so good. But how accurate is the Honor Band 4’s step tracking? I compared it with the Mi Band 2, which is a fairly reliable step tracker. Here are the results I got."
        },
        {
            "type": "imageSingle",
            "text": "https://firebasestorage.googleapis.com/v0/b/logicui-9667a.appspot.com/o/reviews%2Fhonor-band-4-review%2Fimg21.png?alt=media&token=d56a4928-5878-463f-a48a-94c5714d4c6f"
        },
        {
            "type": "text",
            "text": "For walking and jogging, both bands do an equally excellent job, off by less than 5 steps per 100 steps. Both tend to over count when you start increasing your pace, but the readings are still within acceptable range. For most people, the Honor Band 4’s step tracking is good enough."
        },
        {
            "type": "header",
            "text": "Activity Tracking – Run, Cycle, Swim!"
        },
        {
            "type": "subheader",
            "text": "Via Huawei Health App"
        },
        {
            "type": "text",
            "text": "There are 2 ways to start a workout on the Honor Band 4 and both records different things. The first way is starting an “exercise” from the app. This method relies on the GPS of your phone to track your movements, while getting heart rate readings from the Honor Band 4."
        },
        {
            "type": "imageTriple",
            "text": "https://firebasestorage.googleapis.com/v0/b/logicui-9667a.appspot.com/o/reviews%2Fhonor-band-4-review%2Fimg22.jpg?alt=media&token=800ea10e-47a7-43bd-ba7f-dd98af5e46b5"
        },
        {
            "type": "text",
            "text": "Use this method if you want to get a mapped out version of your run. The disadvantage to this is that you have to open the app to use it and you can’t use it to track swimming."
        },
        {
            "type": "imageTriple",
            "text": "https://firebasestorage.googleapis.com/v0/b/logicui-9667a.appspot.com/o/reviews%2Fhonor-band-4-review%2Fimg23.jpg?alt=media&token=7089a600-22c0-42ce-9628-b6bb6b5c22f2"
        },
        {
            "type": "subheader",
            "text": "Via Honor Band 4"
        },
        {
            "type": "text",
            "text": "The other method is to start a workout from the band. You get to select from a list of 6 activities, including swimming. It will prompt you to set your workout goal, in the form of laps/distance, duration or calories. You can also set an alert for when you hit a certain distance."
        },
        {
            "type": "imageSingle",
            "text": "https://firebasestorage.googleapis.com/v0/b/logicui-9667a.appspot.com/o/reviews%2Fhonor-band-4-review%2Fimg24.jpg?alt=media&token=b584118b-6da7-43fa-b0c2-e84afb1e95fb"
        },
        {
            "type": "text",
            "text": "During your workout, the band will show the duration and the distance you traveled. To end a workout, press the capacitive button and tap on the stop icon. The band will display a summary of your workout. To view your workout in greater detail, open the app and tap on “Exercise records”."
        },
        {
            "type": "imageDouble",
            "text": "https://firebasestorage.googleapis.com/v0/b/logicui-9667a.appspot.com/o/reviews%2Fhonor-band-4-review%2Fimg25.jpg?alt=media&token=b483c7fc-c423-4d0b-a1cb-2c2c74ad50db"
        },
        {
            "type": "imageDouble",
            "text": "https://firebasestorage.googleapis.com/v0/b/logicui-9667a.appspot.com/o/reviews%2Fhonor-band-4-review%2Fimg26.jpg?alt=media&token=7a18c41b-2287-499c-8f2b-61423489b5b2"
        },
        {
            "type": "text",
            "text": "For workouts in this mode, you get to see the graphs of your heart rate, pace and cadence aka steps per minute. Tap on the share icon on top and the app will create an image with the details of your workout, which you can save and share. There are a couple of designs you can choose from."
        },
        {
            "type": "imageTriple",
            "text": "https://firebasestorage.googleapis.com/v0/b/logicui-9667a.appspot.com/o/reviews%2Fhonor-band-4-review%2Fimg27.jpg?alt=media&token=3aa34be0-ec3b-4836-987f-a5859fa59ae7"
        },
        {
            "type": "imageTriple",
            "text": "https://firebasestorage.googleapis.com/v0/b/logicui-9667a.appspot.com/o/reviews%2Fhonor-band-4-review%2Fimg28.jpg?alt=media&token=4a3d2219-ee2d-4947-886b-984ab6516d72"
        },
        {
            "type": "imageTriple",
            "text": "https://firebasestorage.googleapis.com/v0/b/logicui-9667a.appspot.com/o/reviews%2Fhonor-band-4-review%2Fimg29.jpg?alt=media&token=fba82529-8efe-443a-a9f0-80568d0a42cd"
        },
        {
            "type": "header",
            "text": "Heart Rate Monitor – More Reliable?"
        },
        {
            "type": "text",
            "text": "By default, continuous heart rate monitoring is off. So the Honor Band 4 will only record your heart rate when you tap “Heart rate” on the display. To record it throughout the day, enable continuous heart rate monitoring in the app. Note that this uses the battery much quicker."
        },
        {
            "type": "imageTriple",
            "text": "https://firebasestorage.googleapis.com/v0/b/logicui-9667a.appspot.com/o/reviews%2Fhonor-band-4-review%2Fimg30.jpg?alt=media&token=28897419-a96b-49a6-9708-cd4a1914d9b1"
        },
        {
            "type": "text",
            "text": "Since my Lifesense Band 2 also supports this feature, I decided to put them against each other. I wore both bands for a day and here are their results. The shapes of both graphs and readings at rest are similar. However, the difference comes when I start to exercise and my heart rate goes above 100 bpm."
        },
        {
            "type": "imageDouble",
            "text": "https://firebasestorage.googleapis.com/v0/b/logicui-9667a.appspot.com/o/reviews%2Fhonor-band-4-review%2Fimg31.jpg?alt=media&token=f3dbd772-dcdc-4b25-a1e3-a9b1e0565a85"
        },
        {
            "type": "imageDouble",
            "text": "https://firebasestorage.googleapis.com/v0/b/logicui-9667a.appspot.com/o/reviews%2Fhonor-band-4-review%2Fimg32.jpg?alt=media&token=12429e5f-5e22-45d6-96f4-78523907863e"
        },
        {
            "type": "text",
            "text": "L - Honor Band 4, R - Lifesense Band 2"
        },
        {
            "type": "text",
            "text": "At the peaks, Honor Band 4’s reading was around 160, while Lifesense Band 2’s was below 140. Considering my age and my pace, the Honor Band 4’s reading made more sense. Also, Lifesense’s heart rate readings increased a little late into my run, so I would say the Honor Band 4 is more accurate."
        },
        {
            "type": "text",
            "text": "Both are not medical devices, so take their readings with a pinch of salt."
        },
        {
            "type": "header",
            "text": "Sleep Tracking – More Meaningful Data"
        },
        {
            "type": "text",
            "text": "To make full use of the Honor Band 4’s sleep tracking capability, enable Huawei TruSleep in the app. How well does it track your sleep? To test that, I put it against the Mi Band 2 and Lifesense Band 2."
        },
        {
            "type": "imageSingle",
            "text": "https://firebasestorage.googleapis.com/v0/b/logicui-9667a.appspot.com/o/reviews%2Fhonor-band-4-review%2Fimg33.jpg?alt=media&token=321e7c19-38b6-4c76-b732-46fc32577ab0"
        },
        {
            "type": "text",
            "text": "Lifesense Band 2 got the start time wrong, while the other 2 were pretty close. For end time, Honor Band 4 was right on the dot. Mi Band 2 was too early and Lifesense Band 2 was 5 minutes too late. While the other 2 only measured deep and light sleep, the Honor Band 4 also measured REM sleep."
        },
        {
            "type": "imageTriple",
            "text": "https://firebasestorage.googleapis.com/v0/b/logicui-9667a.appspot.com/o/reviews%2Fhonor-band-4-review%2Fimg34.jpg?alt=media&token=716ed96e-4054-43c4-a33e-5f92b9793846"
        },
        {
            "type": "imageTriple",
            "text": "https://firebasestorage.googleapis.com/v0/b/logicui-9667a.appspot.com/o/reviews%2Fhonor-band-4-review%2Fimg35.jpg?alt=media&token=1ea41956-f0cf-4410-871d-18fd65a55007"
        },
        {
            "type": "imageTriple",
            "text": "https://firebasestorage.googleapis.com/v0/b/logicui-9667a.appspot.com/o/reviews%2Fhonor-band-4-review%2Fimg36.jpg?alt=media&token=75a5775a-3662-401c-98ac-d3e94d4b76c4"
        },
        {
            "type": "text",
            "text": "L - Honor Band 4, M - Mi Band 2, R - Lifesense Band 2"
        },
        {
            "type": "text",
            "text": "Without professional tools, I am unable to tell how accurate the deep and light sleep are for each band. But neither of them are medical devices, so again, take the results with a grain of salt."
        },
        {
            "type": "header",
            "text": "Battery & Charging – Not Impressive But Not Bad"
        },
        {
            "type": "text",
            "text": "How long the Honor Band 4 lasts on a single charge will depend on what features you enable. But if you get a fitness tracker as feature-packed as this, you will probably want to make full use of all of them. So I tested it with all the key features enabled, including TruSleep and continuous heart rate monitor."
        },
        {
            "type": "text",
            "text": "With that type of usage, I was able to get 3.5 days of usage. Sounds short, but this is the battery life you can expect from most fitness bands with continuous heart rate monitoring. To charge it, simply connect the band to the included charger. It charges from zero to full in 1.5 hours."
        },
        {
            "type": "imageSingle",
            "text": "https://firebasestorage.googleapis.com/v0/b/logicui-9667a.appspot.com/o/reviews%2Fhonor-band-4-review%2Fimg37.jpg?alt=media&token=96120df6-ae4b-423c-9fcf-4095ee7656fa"
        },
        {
            "type": "header",
            "text": "Future Improvements"
        },
        {
            "type": "text",
            "text": "Overall, I am very impressed by what Honor has done with the Honor Band 4. But still, it isn’t flawless. Here are some things I would like to see in the next version of this series."
        },
        {
            "type": "text",
            "text": "Firstly, I would like to see Honor either enable scrolling on the capacitive button, or remove it completely. Right now, it can only wake the display and return to the watch face, which feels kind of a pointless."
        },
        {
            "type": "text",
            "text": "Secondly, there seems to be a bug with the messages feature where I kept receiving duplicate notifications. It is pretty annoying, so I hope Honor can fix that soon."
        },
        {
            "type": "imageSingle",
            "text": "https://firebasestorage.googleapis.com/v0/b/logicui-9667a.appspot.com/o/reviews%2Fhonor-band-4-review%2Fimg38.jpg?alt=media&token=e09b5ea0-9480-4ae9-bb78-b041e97defe9"
        },
        {
            "type": "text",
            "text": "Next, I wish Honor would add magnets to the proprietary connector, to make it easier to attach the band for charging. The current one works but isn’t very convenient. A larger battery would also be appreciated."
        },
        {
            "type": "text",
            "text": "Lastly, it is nice that we can remove the strap, but there isn’t any other official straps we can replace it with right now. I wish Honor would make more straps with different materials."
        }
    ]
}